naitoon/__init__.py
naitoon/error.py
naitoon/http.py
naitoon/naver.py
naitoon/sync.py
naitoon-1.0.0.dist-info/METADATA
naitoon-1.0.0.dist-info/WHEEL
naitoon-1.0.0.dist-info/top_level.txt
naitoon-1.0.0.dist-info/RECORD
