Metadata-Version: 2.1
Name: naitoon
Version: 1.0.0
Summary: 네이버 웹툰 크롤링 라이브러리
Home-page: https://github.com/VoidAsMad/Naitoon
Author: VoidAsMad
Author-email: voidasmad@gmail.com
License: MIT
Platform: UNKNOWN
Requires-Python: >=3.6
